maxwell/__init__.py
maxwell/utils/__init__.py
maxwell/utils/connection.py
maxwell/utils/listenable.py
maxwell/utils/logger.py
maxwell_utils-0.8.1.dist-info/METADATA
maxwell_utils-0.8.1.dist-info/WHEEL
maxwell_utils-0.8.1.dist-info/licenses/LICENSE
maxwell_utils-0.8.1.dist-info/RECORD
