Metadata-Version: 2.3
Name: maxwell-utils
Version: 0.8.1
Summary: The maxwell utils implementation for python.
Project-URL: changelog, https://github.com/maxwell-dev/maxwell-utils-python/CHANGELOG.md
Project-URL: repository, https://github.com/maxwell-dev/maxwell-utils-python
Author-email: Xu Chaoqian <chaoranxu@gmail.com>
License:                                  Apache License
License-File: LICENSE
Classifier: License :: OSI Approved :: MIT License
Classifier: Operating System :: OS Independent
Classifier: Programming Language :: Python :: 3
Requires-Python: >=3.7
Requires-Dist: maxwell-protocol>=0.9.2
Requires-Dist: websockets>=13.0.1
Provides-Extra: test
Requires-Dist: pytest-asyncio>=0.24.0; extra == 'test'
Requires-Dist: pytest-cov>=5.0.0; extra == 'test'
Requires-Dist: pytest>=8.3.2; extra == 'test'
